AIITNLP
