Metadata-Version: 1.0
Name: AIITNLP
Version: 0.3.0
Summary: Ner for bidding
Home-page: https://github.com/choushun/AIITNLP
Author: AIIT
Author-email: zhangjun_dlut@outlook.com
License: MIT Licence
Keywords: pip,Ner,bidding
Platform: any
